{"_id":"5e6836c0-b2f1-11e7-8146-2924d4c3fe6b","name":"anna","location":"new york","skillLevel":"Entry","certification":"true","references":"true","accommodations":"false","workType":"Seasonal","coverLetter":"Hi,\r\nI am an italian girl living in New York since 1 year. I am looking for a seasonal trimming position. I am already in Arcata and I am planning to stay here until the end of december. I have no experience but willing to learn","contact":"please text me at 5182692244","date":"2017-10-17T04:12:20.328Z"}