{"_id":"c7a182a0-adeb-11e7-b8ed-2fed7bd30649","name":"Bob Robbins","location":"Medford, OR","skillLevel":"Entry","certification":"true","references":"true","accommodations":"false","workType":"Part-time","coverLetter":"My availability is open and flexible. I have assisted friends in trimming product over the last few years. I have been a consumer and advocate for cannabis for over 25 years and have an understanding for the differences between Indica, Sativa and hybrids. With basic knowledge of the healing properties of both THC and CBD’s  Thank you for considering my resume for a position in the growing cannabis industry.","contact":"Bobrobbins64@gmail.com","date":"2017-10-10T18:49:44.030Z"}