{"_id":"103f69a0-b882-11e7-a7e2-89cbb3d87b08","name":"Traci Chao","location":"Sacramento","skillLevel":"Senior","certification":"true","references":"true","accommodations":"true","workType":"Full-time","coverLetter":"Hello! My name is Traci and I manage a group of trimmers whom I can bring up to help with the trimming. My trimmers have 4+ yrs. of experience. My group of trimmers are fast and they can help get your product out fast. Feel free to contact me at 916-216-3656 or text and we can talk about it in more detail. We can start a.s.a.p. We work only for cash!\r\n\r\n\r\nThanks!\r\n\r\n\r\nTraci","contact":"traci.chao@sbcglobal.net","date":"2017-10-24T06:10:42.020Z"}