{"_id":"5f3da380-a84e-11e7-8704-5b582ac668d2","name":"Shayla Piso","location":"Whittier, California","skillLevel":"Entry","references":"true","accommodations":"true","workType":"Full-time","coverLetter":"I'm applying for the current position advertised on craigslist.  I'm a very hard worker with exceptional team player attitude as well a strong leadership skills.  I have trimmed on personal use. \r\n\r\nLooking forward to hearing from you.\r\n\r\nBest regards,\r\n\r\nShayla Piso-Morris","contact":"Please contact me @562-284-7669","date":"2017-10-03T15:20:22.014Z"}