{"_id":"91ea5ab0-ab39-11e7-b21f-9dc4de9ce36a","name":"Joseph Hernandez","location":"Oxnard, CA","skillLevel":"Mid","certification":"false","references":"true","accommodations":"false","workType":"Part-time","coverLetter":"Greetings!\r\nJoseph Hernandez \r\n1445 Bayview Dr \r\nOxnard Ca, 93035\r\n(805)401-1961\r\nDOB: 01/05/1996\r\nId like to tell you a little about myself I have about 2 years in Growing and trimming Medical Cannabis . I have gotten to grow and enhance my knowledge from learning and studying all sorts of different strains whether it's a Sativa, hybrid or Indica strain I am very familiar  with Concentrates and edibles as well as cartridges  ! \r\nI got my License and Vehicle ready with gas and looking forward to expanding my knowledge by joining a great Cannabis team !\r\nAVAILABILITY \r\n\r\nMonday 4pm to midnight\r\nTuesday-6am - 2pm\r\nWeds- n/a\r\nThursday-N/a\r\nFriday - All day Available\r\nSat and Sunday 8am to 3pm","contact":"joseph.hernandez89@gmail.com","date":"2017-10-07T08:29:01.175Z"}